MANIFEST.in
README.rst
setup.py
aliyun_python_sdk_ocs.egg-info/PKG-INFO
aliyun_python_sdk_ocs.egg-info/SOURCES.txt
aliyun_python_sdk_ocs.egg-info/dependency_links.txt
aliyun_python_sdk_ocs.egg-info/requires.txt
aliyun_python_sdk_ocs.egg-info/top_level.txt
aliyunsdkocs/__init__.py
aliyunsdkocs/request/__init__.py
aliyunsdkocs/request/v20150301/ActivateInstanceRequest.py
aliyunsdkocs/request/v20150301/AddAuthenticIPRequest.py
aliyunsdkocs/request/v20150301/CreateInstanceRequest.py
aliyunsdkocs/request/v20150301/DataOperateRequest.py
aliyunsdkocs/request/v20150301/DeactivateInstanceRequest.py
aliyunsdkocs/request/v20150301/DeleteInstanceRequest.py
aliyunsdkocs/request/v20150301/DescribeAuthenticIPRequest.py
aliyunsdkocs/request/v20150301/DescribeHistoryMonitorValuesRequest.py
aliyunsdkocs/request/v20150301/DescribeInstancesRequest.py
aliyunsdkocs/request/v20150301/DescribeMonitorItemsRequest.py
aliyunsdkocs/request/v20150301/DescribeMonitorValuesRequest.py
aliyunsdkocs/request/v20150301/DescribeRegionsRequest.py
aliyunsdkocs/request/v20150301/DescribeSecurityIpsRequest.py
aliyunsdkocs/request/v20150301/DescribeZonesRequest.py
aliyunsdkocs/request/v20150301/FlushInstanceRequest.py
aliyunsdkocs/request/v20150301/ModifyHotKeySwitchModeRequest.py
aliyunsdkocs/request/v20150301/ModifyInstanceAttributeRequest.py
aliyunsdkocs/request/v20150301/ModifyInstanceCapacityRequest.py
aliyunsdkocs/request/v20150301/ModifyNetworkTypeRequest.py
aliyunsdkocs/request/v20150301/ModifySecurityIpsRequest.py
aliyunsdkocs/request/v20150301/RemoveAuthenticIPRequest.py
aliyunsdkocs/request/v20150301/ReplaceAuthenticIPRequest.py
aliyunsdkocs/request/v20150301/VerifyPasswordRequest.py
aliyunsdkocs/request/v20150301/__init__.py